{"cameraMode":{"drawMode":0,"name":"Shaded","section":"Shading Mode"},"sceneLighting":false,"audioPlay":false,"sceneViewState":{"showFog":true,"showMaterialUpdate":false,"showSkybox":false,"showFlares":true,"showImageEffects":true,"showParticleSystems":true},"in2DMode":false,"pivot":{"x":5.448564052581787,"y":0.4504524767398834,"z":0.6068135499954224},"rotation":{"x":-0.012654691003262997,"y":-0.7484082579612732,"z":0.014843465760350228,"w":-0.663118302822113},"size":4.306458473205566,"orthographic":false}